heal/__init__.py
heal/cli/__init__.py
heal/cli/extract.py
heal/cli/heal_cli.py
heal/cli/validate.py
heal/cli/vlmd.py
heal/harvard_downloads.py
heal/qdr_downloads.py
heal/utils.py
heal/vlmd/README.md
heal/vlmd/__init__.py
heal/vlmd/config.py
heal/vlmd/extract/conversion.py
heal/vlmd/extract/csv_data_conversion.py
heal/vlmd/extract/csv_dict_conversion.py
heal/vlmd/extract/extract.py
heal/vlmd/extract/json_dict_conversion.py
heal/vlmd/extract/redcap_csv_dict_conversion.py
heal/vlmd/extract/utils.py
heal/vlmd/file_utils.py
heal/vlmd/mappings/__init__.py
heal/vlmd/mappings/names.py
heal/vlmd/mappings/redcap_csv_headers.py
heal/vlmd/mappings/redcap_field_mapping.py
heal/vlmd/mappings/typesets.py
heal/vlmd/mappings/values.py
heal/vlmd/mappings/versions.py
heal/vlmd/schemas/heal_csv.json
heal/vlmd/schemas/heal_json.json
heal/vlmd/utils.py
heal/vlmd/validate/json_validator.py
heal/vlmd/validate/utils.py
heal/vlmd/validate/validate.py
heal_sdk-1.1.2.dist-info/METADATA
heal_sdk-1.1.2.dist-info/WHEEL
heal_sdk-1.1.2.dist-info/entry_points.txt
heal_sdk-1.1.2.dist-info/licenses/LICENSE
heal_sdk-1.1.2.dist-info/licenses/NOTICE
heal_sdk-1.1.2.dist-info/RECORD
