Metadata-Version: 2.4
Name: heal-sdk
Version: 1.1.2
Summary: HEAL Platform SDK
License: Apache-2.0
License-File: LICENSE
License-File: NOTICE
Author: Center for Translational Data Science at the University of Chicago
Author-email: support@gen3.org
Requires-Python: >=3.9,<4.0
Classifier: License :: OSI Approved :: Apache Software License
Classifier: Programming Language :: Python :: 3
Classifier: Programming Language :: Python :: 3.9
Classifier: Programming Language :: Python :: 3.10
Classifier: Programming Language :: Python :: 3.11
Classifier: Programming Language :: Python :: 3.12
Classifier: Programming Language :: Python :: 3.13
Classifier: Programming Language :: Python :: 3.14
Requires-Dist: cdislogging (>=1.1.0,<2.0.0)
Requires-Dist: gen3 (>=4.22.4,<5.0.0)
Requires-Dist: imagehash (>=4.3.2,<5.0.0)
Requires-Dist: requests
Requires-Dist: visions (>=0.7.5)
